tests/__init__.py
tests/test_analyzer.py
tests/test_utils.py
text_analyzer/__init__.py
text_analyzer/analyzer.py
text_analyzer/utils.py
text_analyzer_toolkit-0.1.0.dist-info/licenses/LICENSE
text_analyzer_toolkit-0.1.0.dist-info/METADATA
text_analyzer_toolkit-0.1.0.dist-info/WHEEL
text_analyzer_toolkit-0.1.0.dist-info/top_level.txt
text_analyzer_toolkit-0.1.0.dist-info/RECORD
