Metadata-Version: 2.4
Name: text-analyzer-toolkit
Version: 0.1.0
Summary: A simple text analysis toolkit for basic text processing tasks
Home-page: https://github.com/ZoeDuan/text-analyzer-toolkit
Author: Zoe Duan
Author-email: Zoe Duan <zoe_dyh@hotmail.com>
License: MIT License
Project-URL: Homepage, https://github.com/ZoeDuan/text-analyzer-toolkit
Project-URL: Repository, https://github.com/ZoeDuan/text-analyzer-toolkit.git
Project-URL: Bug Tracker, https://github.com/ZoeDuan/text-analyzer-toolkit/issues
Classifier: Development Status :: 3 - Alpha
Classifier: Intended Audience :: Developers
Classifier: License :: OSI Approved :: MIT License
Classifier: Operating System :: OS Independent
Classifier: Programming Language :: Python :: 3
Requires-Python: >=3.7
License-File: LICENSE
Provides-Extra: dev
Requires-Dist: pytest>=6.0; extra == "dev"
Requires-Dist: black; extra == "dev"
Requires-Dist: flake8; extra == "dev"
Requires-Dist: mypy; extra == "dev"
Dynamic: author
Dynamic: home-page
Dynamic: license-file
Dynamic: requires-python
